dotfiles_maintainer/__init__.py
dotfiles_maintainer/cli.py
dotfiles_maintainer/config.py
dotfiles_maintainer/server.py
dotfiles_maintainer/core/__init__.py
dotfiles_maintainer/core/memory.py
dotfiles_maintainer/core/types.py
dotfiles_maintainer/prompts/Persona.md
dotfiles_maintainer/prompts/__init__.py
dotfiles_maintainer/prompts/memory.py
dotfiles_maintainer/prompts/persona.py
dotfiles_maintainer/tools/__init__.py
dotfiles_maintainer/tools/baseline.py
dotfiles_maintainer/tools/changes.py
dotfiles_maintainer/tools/drift.py
dotfiles_maintainer/tools/health.py
dotfiles_maintainer/tools/history.py
dotfiles_maintainer/tools/lifecycle.py
dotfiles_maintainer/tools/queries.py
dotfiles_maintainer/tools/roadmap.py
dotfiles_maintainer/tools/trials.py
dotfiles_maintainer/tools/troubleshooting.py
dotfiles_maintainer/tools/updates.py
dotfiles_maintainer/utils/__init__.py
dotfiles_maintainer/utils/secrets.py
dotfiles_maintainer/utils/vcs.py
dotfiles_maintainer-1.0.1.dist-info/METADATA
dotfiles_maintainer-1.0.1.dist-info/WHEEL
dotfiles_maintainer-1.0.1.dist-info/entry_points.txt
dotfiles_maintainer-1.0.1.dist-info/licenses/LICENSE
dotfiles_maintainer-1.0.1.dist-info/RECORD
