Metadata-Version: 2.4
Name: dotfiles-maintainer
Version: 1.0.1
Summary: An MCP server for managing dotfiles with semantic memory and context awareness.
Project-URL: Homepage, https://github.com/lonlydwolf/dotfiles-maintainer
Project-URL: Repository, https://github.com/lonlydwolf/dotfiles-maintainer
Project-URL: Issues, https://github.com/lonlydwolf/dotfiles-maintainer/issues
Author-email: Ahmad Mollaei <The.AhmadMollaei@proton.me>
License: Apache-2.0
License-File: LICENSE
Keywords: configuration,dotfiles,mcp,semantic-memory
Classifier: Development Status :: 4 - Beta
Classifier: Intended Audience :: Developers
Classifier: License :: OSI Approved :: Apache Software License
Classifier: Programming Language :: Python :: 3.10
Classifier: Programming Language :: Python :: 3.11
Classifier: Programming Language :: Python :: 3.12
Classifier: Programming Language :: Python :: 3.13
Requires-Python: >=3.10
Requires-Dist: anthropic>=0.76.0
Requires-Dist: detect-secrets>=1.5.0
Requires-Dist: google-genai>=1.57.0
Requires-Dist: langchain-community>=0.4.1
Requires-Dist: langchain-huggingface>=0.1.2
Requires-Dist: langchain>=0.3.0
Requires-Dist: mcp<2,>=1.25
Requires-Dist: mem0ai>=1.0.2
Requires-Dist: ollama>=0.6.1
Requires-Dist: pydantic-settings>=2.0
Requires-Dist: pydantic>=2.0
Requires-Dist: sentence-transformers>=5.2.0
Requires-Dist: typer>=0.9.0
